tracardi_graph_runner/__init__.py
tracardi_graph_runner/domain/__init__.py
tracardi_graph_runner/domain/connection.py
tracardi_graph_runner/domain/dag_graph.py
tracardi_graph_runner/domain/dag_protection.py
tracardi_graph_runner/domain/debug_call_info.py
tracardi_graph_runner/domain/debug_info.py
tracardi_graph_runner/domain/edge.py
tracardi_graph_runner/domain/edges.py
tracardi_graph_runner/domain/entity.py
tracardi_graph_runner/domain/error_debug_info.py
tracardi_graph_runner/domain/execution_graph.py
tracardi_graph_runner/domain/flow.py
tracardi_graph_runner/domain/flow_graph_data.py
tracardi_graph_runner/domain/flow_history.py
tracardi_graph_runner/domain/init_result.py
tracardi_graph_runner/domain/input_params.py
tracardi_graph_runner/domain/named_entity.py
tracardi_graph_runner/domain/node.py
tracardi_graph_runner/domain/nodes.py
tracardi_graph_runner/domain/port_to_port_edges.py
tracardi_graph_runner/domain/tasks_results.py
tracardi_graph_runner/domain/work_flow.py
tracardi_graph_runner/domain/__pycache__/__init__.cpython-37.pyc
tracardi_graph_runner/domain/__pycache__/__init__.cpython-38.pyc
tracardi_graph_runner/domain/__pycache__/connection.cpython-37.pyc
tracardi_graph_runner/domain/__pycache__/connection.cpython-38.pyc
tracardi_graph_runner/domain/__pycache__/dag_graph.cpython-37.pyc
tracardi_graph_runner/domain/__pycache__/dag_graph.cpython-38.pyc
tracardi_graph_runner/domain/__pycache__/debug_call_info.cpython-37.pyc
tracardi_graph_runner/domain/__pycache__/debug_call_info.cpython-38.pyc
tracardi_graph_runner/domain/__pycache__/debug_info.cpython-37.pyc
tracardi_graph_runner/domain/__pycache__/debug_info.cpython-38.pyc
tracardi_graph_runner/domain/__pycache__/edge.cpython-37.pyc
tracardi_graph_runner/domain/__pycache__/edge.cpython-38.pyc
tracardi_graph_runner/domain/__pycache__/edges.cpython-37.pyc
tracardi_graph_runner/domain/__pycache__/edges.cpython-38.pyc
tracardi_graph_runner/domain/__pycache__/entity.cpython-37.pyc
tracardi_graph_runner-0.6.13.dist-info/METADATA
tracardi_graph_runner-0.6.13.dist-info/WHEEL
tracardi_graph_runner-0.6.13.dist-info/top_level.txt
tracardi_graph_runner-0.6.13.dist-info/RECORD
