Metadata-Version: 2.1
Name: tracardi-graph-runner
Version: 0.6.13
Summary: Tracardi Graph Runner
Home-page: UNKNOWN
Author: Risto Kowaczewski
Author-email: risto.kowaczewski@gmail.com
License: UNKNOWN
Platform: UNKNOWN
Classifier: Programming Language :: Python :: 3
Classifier: License :: Other/Proprietary License
Classifier: Operating System :: OS Independent
Requires-Dist: pydantic
Requires-Dist: asyncio
Requires-Dist: tracardi-plugin-sdk (>=0.6.30)
Requires-Dist: dotty-dict
